<?xml version="1.0" encoding="UTF-8" ?>
<!DOCTYPE mapper
PUBLIC "-//mybatis.org//DTD Mapper 3.0//EN"
"http://mybatis.org/dtd/mybatis-3-mapper.dtd">
<mapper namespace="cart">

	<insert id="cart_insert" parameterType="cart">
		INSERT INTO cart VALUES(seq_cart_idx.nextval, #{m_num}, #{g_num}, #{g_price}, #{count}, DEFAULT , #{g_name})
	</insert>
	
	<select id="cart_list" resultType="cart">
		select * from cart where m_num=#{m_num} order by idx desc
	</select>
	
	<!-- 회원별 카트의 수량 업데이트 -->
	<update id="cart_update" parameterType="java.util.HashMap">
		update cart set count = count + #{count} where g_num=#{g_num}
	</update>
	
	<update id="cart_cnt_update" parameterType="java.util.HashMap" >
		update cart set count=#{count} where g_num=#{g_num} and m_num=#{m_num}
	</update>
	
	<select id="cart_one" resultType="cart" >
		select * from cart where m_num=#{m_num} and g_num=#{g_num}
	</select>
	
	<select id="selectCart" resultType="cart" >
		select * from cart where m_num=#{m_num} and g_num=#{g_num}
	</select>	
	
	<!-- 장바구니 상품삭제 -->
	<delete id="delete_cart" parameterType="java.util.HashMap">
	delete from cart where idx=#{idx} and m_num=#{m_num}
	</delete>

</mapper>